httpie_consul.py
httpie_consul-1.0.2.dist-info/METADATA
httpie_consul-1.0.2.dist-info/RECORD
httpie_consul-1.0.2.dist-info/WHEEL
httpie_consul-1.0.2.dist-info/entry_points.txt
httpie_consul-1.0.2.dist-info/top_level.txt
