Metadata-Version: 2.1
Name: httpie-consul
Version: 1.0.2
Summary: Consul plugin for HTTPie.
Home-page: https://github.com/ar4s/httpie-consul
Author: Arkadiusz Adamski
Author-email: arkadiusz.adamski@gmail.com
License: BSD
Download-URL: https://github.com/ar4s/httpie-consul
Platform: UNKNOWN
Classifier: Development Status :: 5 - Production/Stable
Classifier: Programming Language :: Python
Classifier: Environment :: Plugins
Classifier: License :: OSI Approved :: BSD License
Classifier: Topic :: Internet :: WWW/HTTP
Classifier: Topic :: Utilities
Requires-Dist: httpie (>=0.7.0)
Requires-Dist: consulate (>=0.6.0)
